{"translation-revision-date":"2026-02-16 12:03+0000","generator":"Loco https:\/\/localise.biz\/","source":"assets\/client\/admin\/chunks\/homescreen.js","domain":"woocommerce","locale_data":{"woocommerce":{"":{"domain":"","lang":"it_IT","plural-forms":"nplurals=2; plural=n != 1;"},"Try the new templates":["Prova i nuovi template"],"Store emails have had an upgrade!":["Le e-mail del negozio sono state aggiornate."],"Customize your emails":["Personalizza le tue e-mail"],"Your store emails have had an upgrade!":["Le e-mail del tuo negozio sono state aggiornate."],"Google for WooCommerce":["Google per WooCommerce"],"WooPayments":["WooPayments"],"TikTok for WooCommerce":["TikTok per WooCommerce"],"Welcome to %s":["Benvenuto a %s"],"Pinterest for WooCommerce":["Pinterest per WooCommerce"],"MailPoet":["MailPoet"],"Razorpay":["Razorpay"],"Store details":["Dettagli negozio"],"Undo":["Annulla"],"Facebook for WooCommerce":["Facebook per WooCommerce"],"Mailchimp for WooCommerce":["MailChimp for WooCommerce"],"Klarna Payments for WooCommerce":["Klarna Payments per WooCommerce"],"Klarna Checkout for WooCommerce":["Klarna Checkout for WooCommerce"],"Jetpack":["Jetpack"],"Extensions":["Estensioni"],"Dismiss":["Ignora"],"Approve":["Approva"],"%d product":["%d prodotto","%d prodotti"],"Marketing":["Marketing"],"Add products":["Aggiungi prodotti"],"Save":["Salva"],"Tax":["Imposte"],"Learn more":["Per saperne di pi\u00f9"],"Close":["Chiudi"],"Shipping":["Spedizione"],"Payments":["Pagamenti"],"Orders":["Ordini"],"Cancel":["Annulla"],"Stock":["Magazzino"],"Reviews":["Recensioni"],"Delete":["Elimina"],"Settings":["Impostazioni"],"Metro Manila":["Metro Manila"],"Roma":["Roma"]}}}